<annotation>
	<folder>data</folder>
	<filename>20230705175637_20230705175637.jpg</filename>
	<path>C:\Users\Ivan Lee\Documents\Software project\Machine learning\AI\CPOS\AI-TrainData-PscalVOC-and-Yolo-CarTypeRecognition\data\20230705175637_20230705175637.jpg</path>
	<source>
		<database>Unknown</database>
	</source>
	<size>
		<width>1920</width>
		<height>1080</height>
		<depth>3</depth>
	</size>
	<segmented>0</segmented>
	<object>
		<name>truck_large</name>
		<pose>Unspecified</pose>
		<truncated>1</truncated>
		<difficult>0</difficult>
		<bndbox>
			<xmin>1258</xmin>
			<ymin>18</ymin>
			<xmax>1920</xmax>
			<ymax>953</ymax>
		</bndbox>
	</object>
</annotation>
